{
    "$schema": "https://schema.management.azure.com/schemas/2015-01-01/deploymentParameters.json#",
    "contentVersion": "1.0.0.0",
  "parameters": {
    "vmName": {
      "value": ""
    },
    "localAdminUserName": {
      "value": ""
    },
    "localAdminPassword": {
      "value": ""
    },
    "domainJoinUserName": {
      "value": ""
    },
    "domainJoinPassword": {
      "value": ""
    },
    "localAdmins": {
      "value": ""
    },
    "appID": {
      "value": ""
    },
    "orgID": {
      "value": ""
    },
    "domainName": {
      "value": ""
    },
    "env": {
      "value": ""
    },
    "imagePublisher": {
      "value": ""
    },
    "imageOffer": {
      "value": ""
    },
    "sku": {
      "value": ""
    },
    "snoozeDate": {
      "value": ""
    },
    "storageAccountType": {
      "value": ""
    },
    "userImageStorageAccountName": {
      "value": ""
    },
    "numberOfInstances": {
      "value": 1
    },
    "virtualNetwork": {
      "value": "1"
    },
    "vnetResourceGroup": {
      "value": ""
    },
    "subnetName": {
      "value": "Subnet-1"
    },
    "subnetPrefix": {
      "value": "10.0.0.0/24"
    },
    "vmSize": {
      "value": "Standard_A2"
    },
    "ServerRole": {
      "value": "App"
    },
    "DiskSize": {
      "value": "200"
    },
    "DiskCount": {
      "value": "1"
    },
    "ouPath": {
      "value": ""
    }
  }
}